MANIFEST.in
README.md
paulgraham_text.txt
setup.py
recurrent_js_python.egg-info/PKG-INFO
recurrent_js_python.egg-info/SOURCES.txt
recurrent_js_python.egg-info/dependency_links.txt
recurrent_js_python.egg-info/not-zip-safe
recurrent_js_python.egg-info/requires.txt
recurrent_js_python.egg-info/top_level.txt
recurrentjs/__init__.py