Metadata-Version: 1.1
Name: recurrent-js-python
Version: 0.0.1
Summary: Python implementation of Andrej Kaparthy's recurrentjs library
Home-page: https://github.com/JonathanRaiman/recurrentjs
Author: Jonathan Raiman
Author-email: jraiman at mit dot edu
License: MIT
Download-URL: https://github.com/JonathanRaiman/recurrentjs
Keywords: Gradient Descent,LSTM,neural networks,automatic differentiation
Platform: any
Classifier: Intended Audience :: Science/Research
Classifier: Operating System :: OS Independent
Classifier: Programming Language :: Python :: 3.3
Classifier: Programming Language :: Python :: 2.7
Classifier: Topic :: Scientific/Engineering :: Artificial Intelligence
Classifier: Topic :: Scientific/Engineering :: Mathematics
